ChangeLog
LICENSE
MANIFEST.in
README.rst
setup.py
docs/Makefile
docs/source/changelog.rst
docs/source/conf.py
docs/source/debug.rst
docs/source/document.rst
docs/source/formatter.rst
docs/source/gadgets.rst
docs/source/highlighter.rst
docs/source/index.rst
docs/source/license.rst
docs/source/parceqt.rst
docs/source/pkginfo.rst
docs/source/treebuilder.rst
docs/source/treemodel.rst
docs/source/util.rst
docs/source/widgets.rst
docs/source/work.rst
docs/source/_static/custom.css
parceqt/__init__.py
parceqt/debug.py
parceqt/document.py
parceqt/formatter.py
parceqt/highlighter.py
parceqt/pkginfo.py
parceqt/treebuilder.py
parceqt/treemodel.py
parceqt/util.py
parceqt/work.py
parceqt.egg-info/PKG-INFO
parceqt.egg-info/SOURCES.txt
parceqt.egg-info/dependency_links.txt
parceqt.egg-info/top_level.txt
parceqt/gadgets/__init__.py
parceqt/gadgets/extraselectionmanager.py
parceqt/gadgets/languagemenuaction.py
parceqt/widgets/__init__.py
parceqt/widgets/lexiconchooser.py