Metadata-Version: 2.1
Name: parceqt
Version: 0.33.0
Summary: The parceqt Python module
Home-page: https://github.com/wbsoft/parceqt
Maintainer: Wilbert Berendsen
Maintainer-email: info@wilbertberendsen.nl
License: GPL
Platform: UNKNOWN
Classifier: Development Status :: 3 - Alpha
Classifier: Intended Audience :: Developers
Classifier: License :: OSI Approved :: GNU General Public License v3 or later (GPLv3+)
Classifier: Programming Language :: Python :: 3.3
Classifier: Topic :: Text Processing
Classifier: Environment :: X11 Applications :: Qt
License-File: LICENSE
